modulefgoiriz1/__init__.py
modulefgoiriz1-0.1.0.dist-info/WHEEL
modulefgoiriz1-0.1.0.dist-info/METADATA
modulefgoiriz1-0.1.0.dist-info/RECORD
