Metadata-Version: 2.1
Name: modulefgoiriz1
Version: 0.1.0
Summary: My super cool Python module.
Author-email: modulefgoiriz1 <modulefgoiriz1@example.com>
